{
    "format_version": 3,
    "tooth": "github.com/VincentZyu233/levilamina-plugin-serverinfo-rest",
    "version": "1.0.0",
    "info": {
        "name": "serverinfo-rest",
        "description": "A LeviLamina plugin that provides REST API for server information",
        "author": "VincentZyu",
        "tags": [
            "levilamina",
            "ll",
            "plugin",
            "rest",
            "api",
            "server-info"
        ]
    },
    "dependencies": {
        "github.com/LiteLDev/LeviLamina": ">=1.0.0"
    },
    "files": {
        "place": [
            {
                "src": "serverinfo-rest/*",
                "dest": "plugins/serverinfo-rest/"
            }
        ]
    }
}
